mcvsphere/__init__.py
mcvsphere/audit.py
mcvsphere/auth.py
mcvsphere/config.py
mcvsphere/connection.py
mcvsphere/middleware.py
mcvsphere/permissions.py
mcvsphere/py.typed
mcvsphere/server.py
mcvsphere/mixins/__init__.py
mcvsphere/mixins/console.py
mcvsphere/mixins/disk_management.py
mcvsphere/mixins/guest_ops.py
mcvsphere/mixins/host_management.py
mcvsphere/mixins/monitoring.py
mcvsphere/mixins/nic_management.py
mcvsphere/mixins/ovf_management.py
mcvsphere/mixins/power_ops.py
mcvsphere/mixins/resources.py
mcvsphere/mixins/serial_port.py
mcvsphere/mixins/snapshots.py
mcvsphere/mixins/vcenter_ops.py
mcvsphere/mixins/vm_lifecycle.py
mcvsphere-0.2.2.dist-info/METADATA
mcvsphere-0.2.2.dist-info/WHEEL
mcvsphere-0.2.2.dist-info/entry_points.txt
mcvsphere-0.2.2.dist-info/licenses/LICENSE
mcvsphere-0.2.2.dist-info/RECORD
