Metadata-Version: 2.4
Name: mcvsphere
Version: 0.2.2
Summary: Model Control for vSphere - AI-driven VMware virtual machine management via MCP
Project-URL: Homepage, https://git.supported.systems/MCP/mcvsphere
Project-URL: Repository, https://git.supported.systems/MCP/mcvsphere
Author-email: Ryan Malloy <ryan@supported.systems>
License-Expression: MIT
License-File: LICENSE
Keywords: esxi,fastmcp,mcp,model-context-protocol,vcenter,virtualization,vmware,vsphere
Classifier: Development Status :: 4 - Beta
Classifier: Intended Audience :: Developers
Classifier: Intended Audience :: System Administrators
Classifier: License :: OSI Approved :: MIT License
Classifier: Programming Language :: Python :: 3
Classifier: Programming Language :: Python :: 3.11
Classifier: Programming Language :: Python :: 3.12
Classifier: Topic :: System :: Systems Administration
Requires-Python: >=3.11
Requires-Dist: fastmcp>=2.14.1
Requires-Dist: pydantic-settings>=2.0
Requires-Dist: pydantic>=2.0
Requires-Dist: pyvmomi>=8.0
Requires-Dist: pyyaml>=6.0
Provides-Extra: dev
Requires-Dist: pytest-asyncio>=0.24; extra == 'dev'
Requires-Dist: pytest>=8.0; extra == 'dev'
Requires-Dist: ruff>=0.8; extra == 'dev'
